setup.py
cart/__init__.py
cart/cart.py
cart/models.py
cart/tests.py
cart/views.py
cart/migrations/0001_initial.py
cart/migrations/__init__.py
django_cart.egg-info/PKG-INFO
django_cart.egg-info/SOURCES.txt
django_cart.egg-info/dependency_links.txt
django_cart.egg-info/top_level.txt