Metadata-Version: 1.0
Name: django-cart
Version: 1.0.0
Summary: Django simple shopping cart, tests and south migrations included
Home-page: https://github.com/bmentges/django-cart
Author: Bruno Carvalho
Author-email: bmentges@gmail.com
License: GNU v3
Platform: UNKNOWN
Classifier: Development Status :: 5 - Production/Stable
Classifier: Environment :: Web Environment
Classifier: Framework :: Django
Classifier: Intended Audience :: Developers
Classifier: License :: OSI Approved :: BSD License
Classifier: Operating System :: OS Independent
Classifier: Programming Language :: Python
Classifier: Topic :: Software Development :: Libraries :: Python Modules
